faker_books/__init__.py
faker_books/_authors.py
faker_books/_genres.py
faker_books/_publishers.py
faker_books/_titles.py
faker_books/provider.py
faker_books-0.1.0.dist-info/licenses/LICENSE
faker_books-0.1.0.dist-info/METADATA
faker_books-0.1.0.dist-info/WHEEL
faker_books-0.1.0.dist-info/top_level.txt
faker_books-0.1.0.dist-info/RECORD
