Metadata-Version: 2.4
Name: faker-books
Version: 0.1.0
Summary: A community Faker provider for book-related data.
Author-email: Maximos Nikiforakis <nikiforos@live.co.uk>
License-Expression: MIT
Project-URL: Homepage, https://github.com/Maxcode123/faker_books
Keywords: faker,books
Requires-Python: >=3.13
License-File: LICENSE
Requires-Dist: faker>=37.3.0
Dynamic: license-file
